redis_json_logger/__init__.py
redis_json_logger/formatter.py
redis_json_logger/handler.py
redis_json_logger-0.3.0.dist-info/METADATA
redis_json_logger-0.3.0.dist-info/WHEEL
redis_json_logger-0.3.0.dist-info/top_level.txt
redis_json_logger-0.3.0.dist-info/RECORD
