Metadata-Version: 2.1
Name: redis-json-logger
Version: 0.3.0
Summary: An extension of Python's built-in logger
Home-page: https://github.com/jerinpetergeorge/python-json-logger
Author: Jerin Peter George
Author-email: jerinpetergeorge@gmail.com
License: MIT-Zero
Download-URL: https://github.com/jerinpetergeorge/python-json-logger/tarball/0.3.0
Platform: UNKNOWN
Classifier: Programming Language :: Python :: 3
Classifier: Operating System :: OS Independent
Requires-Dist: redis
